setup.py
berval_distributions.egg-info/PKG-INFO
berval_distributions.egg-info/SOURCES.txt
berval_distributions.egg-info/dependency_links.txt
berval_distributions.egg-info/not-zip-safe
berval_distributions.egg-info/top_level.txt
distributions/Binomialdistribution.py
distributions/Gaussiandistribution.py
distributions/Generaldistribution.py
distributions/__init__.py