Metadata-Version: 1.0
Name: berval-distributions
Version: 1.2
Summary: Gaussian and Binomial distributions
Home-page: UNKNOWN
Author: camberval
Author-email: cam@gmail.com
License: UNKNOWN
Platform: UNKNOWN
